iex_cppparser/__init__.py
iex_cppparser/compile_cpp.py
iex_cppparser/download.py
iex_cppparser/logger.py
iex_cppparser/which_bash.py
iex_cppparser/bin/iex_parser.out
iex_cppparser/bin/iex_parser_all_threaded.out
iex_cppparser/bin/iex_parser_split.out
iex_cppparser/bin/iex_parser_threaded.out
iex_cppparser/cpp/decode_messages.cpp
iex_cppparser/cpp/decode_messages.h
iex_cppparser/cpp/iex_parser.cpp
iex_cppparser/cpp/iex_parser.out
iex_cppparser/cpp/iex_parser_all_threaded.cpp
iex_cppparser/cpp/iex_parser_all_threaded.out
iex_cppparser/cpp/iex_parser_split.cpp
iex_cppparser/cpp/iex_parser_split.out
iex_cppparser/cpp/iex_parser_threaded.cpp
iex_cppparser/cpp/iex_parser_threaded.out
iex_cppparser/cpp/logger.cpp
iex_cppparser/cpp/logger.h
iex_cppparser/cpp/main.cpp
iex_cppparser-1.0.3.dist-info/METADATA
iex_cppparser-1.0.3.dist-info/WHEEL
iex_cppparser-1.0.3.dist-info/licenses/LICENSE
iex_cppparser-1.0.3.dist-info/RECORD
