Metadata-Version: 2.3
Name: iex-cppparser
Version: 1.0.3
Summary: A downloader and parser for IEX DEEP historical data using C++ backend.
Project-URL: Source, https://github.com/Sai271828/iex-parser
Project-URL: Documentation, https://iex-parser.readthedocs.io/
Author-email: Karthik Vasu <karthikvasu09@gmail.com>, Venkata Sai Bavisetty <venkatasainarayana@gmail.com>
License-File: LICENSE
Classifier: License :: OSI Approved :: BSD License
Classifier: Operating System :: Unix
Classifier: Programming Language :: Python :: 3
Requires-Python: >=3.7
Requires-Dist: pytest
Requires-Dist: requests>=2.25.1
Requires-Dist: tqdm>=4.62.3
